djangaudit/__init__.py
djangaudit/apps.py
djangaudit/lib.py
djangaudit/management/__init__.py
djangaudit/management/commands/__init__.py
djangaudit/management/commands/audit_project.py
djangaudit-0.1.1.dist-info/LICENCE
djangaudit-0.1.1.dist-info/METADATA
djangaudit-0.1.1.dist-info/WHEEL
djangaudit-0.1.1.dist-info/top_level.txt
djangaudit-0.1.1.dist-info/RECORD
