Metadata-Version: 2.1
Name: djangaudit
Version: 0.1.1
Summary: A Django app for auditing a django project
Home-page: https://github.com/tominardi/djangaudit
Author: Thomas Durey
Author-email: tominardi@gmail.com
License: MIT License
Project-URL: Source, https://bitbucket.org/tominardi/djangaudit/
Platform: UNKNOWN
Classifier: Environment :: Web Environment
Classifier: Framework :: Django
Classifier: Framework :: Django :: 3.0
Classifier: Intended Audience :: Developers
Classifier: License :: OSI Approved :: MIT License
Classifier: Operating System :: OS Independent
Classifier: Programming Language :: Python
Classifier: Programming Language :: Python :: 3
Classifier: Programming Language :: Python :: 3.7
Classifier: Programming Language :: Python :: 3.8
Classifier: Programming Language :: Python :: 3.9
Classifier: Programming Language :: Python :: 3.10
Classifier: Programming Language :: Python :: 3.11
Classifier: Programming Language :: Python :: 3.12
Classifier: Topic :: Internet :: WWW/HTTP
Classifier: Topic :: Internet :: WWW/HTTP :: Dynamic Content
Requires-Python: >=3.7
License-File: LICENCE
Requires-Dist: Django>=3.0
Requires-Dist: requests
